litehttp/__init__.py
litehttp/exceptions/__init__.py
litehttp/exceptions/baseexception.py
litehttp/exceptions/server_exception/__init__.py
litehttp/exceptions/server_exception/base_web_exception.py
litehttp/exceptions/server_exception/server_e.py
litehttp/http/__init__.py
litehttp/http/middlewares.py
litehttp/http/request_obj.py
litehttp/http/responses.py
litehttp/http/webserver.py
litehttp/http/route/__init__.py
litehttp/http/route/routing.py
litehttp/http/templates/__init__.py
litehttp/http/templates/render.py
litehttp/http/templates/extensions/__init__.py
litehttp/http/templates/extensions/base_extension.py
litehttp/http/templates/extensions/project_extensions.py
litehttp-0.0.6.dist-info/METADATA
litehttp-0.0.6.dist-info/WHEEL
litehttp-0.0.6.dist-info/top_level.txt
litehttp-0.0.6.dist-info/RECORD
