Metadata-Version: 2.1
Name: litehttp
Version: 0.0.6
Summary: Http framework.
Classifier: Programming Language :: Python :: 3
Requires-Python: >=3.7
Requires-Dist: gunicorn
Requires-Dist: Jinja2
